iseq/__init__.py
iseq/_testit.py
iseq/_version.py
iseq/alphabet.py
iseq/codon.py
iseq/codon_table.py
iseq/codon_usage.py
iseq/codon_usage_20200706.pkl.xz
iseq/conftest.py
iseq/example.py
iseq/fragment.py
iseq/gencode.py
iseq/hmmer_model.py
iseq/model.py
iseq/profile.py
iseq/random.py
iseq/result.py
iseq/typing.py
iseq/wrap.py
iseq/_cli/__init__.py
iseq/_cli/_cli.py
iseq/_cli/amino_decode.py
iseq/_cli/bscan.py
iseq/_cli/debug_writer.py
iseq/_cli/gff_filter.py
iseq/_cli/hscan.py
iseq/_cli/output_writer.py
iseq/_cli/press.py
iseq/_cli/pscan.py
iseq/_cli/pscan2.py
iseq/_cli/pscan3.py
iseq/_cli/strip.py
iseq/_cli/_plot/__init__.py
iseq/_cli/_plot/_cli.py
iseq/_cli/_plot/e_value_dist.py
iseq/_cli/_plot/length_ratio.py
iseq/_cli/_plot/profile_dist.py
iseq/_cli/test/__init__.py
iseq/_cli/test/conftest.py
iseq/_cli/test/test_cli_amino_decode.py
iseq/_cli/test/test_cli_bscan.py
iseq/_cli/test/test_cli_hscan.py
iseq/_cli/test/test_cli_pscan.py
iseq/_cli/test/test_cli_pscan2.py
iseq/_cli/test/test_cli_pscan3.py
iseq/gff/__init__.py
iseq/gff/_gff.py
iseq/gff/test/__init__.py
iseq/gff/test/test_gff.py
iseq/hmmer3/__init__.py
iseq/hmmer3/_profile.py
iseq/hmmer3/typing.py
iseq/protein/__init__.py
iseq/protein/_fragment.py
iseq/protein/_profile.py
iseq/protein/typing.py
iseq/test/__init__.py
iseq/test/test_codon_table.py
iseq/test/test_codon_usage.py
iseq/test/test_gencode.py
iseq/test/test_hmmdata.py
iseq/test/test_hmmer3.py
iseq/test/test_hmmer3_compat.py
iseq/test/test_protein.py
iseq/test/test_random.py
iseq-0.0.13.dist-info/LICENSE.md
iseq-0.0.13.dist-info/METADATA
iseq-0.0.13.dist-info/WHEEL
iseq-0.0.13.dist-info/entry_points.txt
iseq-0.0.13.dist-info/top_level.txt
iseq-0.0.13.dist-info/zip-safe
iseq-0.0.13.dist-info/RECORD
