Metadata-Version: 2.1
Name: iseq
Version: 0.0.13
Summary: Invisible sequence scanner
Home-page: https://github.com/EBI-Metagenomics/iseq
Author: Danilo Horta
Author-email: horta@ebi.ac.uk
Maintainer: Danilo Horta
Maintainer-email: horta@ebi.ac.uk
License: MIT
Download-URL: https://github.com/EBI-Metagenomics/iseq
Keywords: hmm,profile,dna,protein
Platform: Windows
Platform: MacOS
Platform: Linux
Classifier: Development Status :: 5 - Production/Stable
Classifier: License :: OSI Approved :: MIT License
Classifier: Operating System :: OS Independent
Classifier: Programming Language :: Python
Requires-Dist: assertpy (>=1.1)
Requires-Dist: biopython (>=1.78)
Requires-Dist: click (>=7.0.0)
Requires-Dist: fasta-reader (>=1.0.0)
Requires-Dist: hmmer-reader (>=0.0.14)
Requires-Dist: hmmer (>=0.0.12)
Requires-Dist: imm (>=0.0.2)
Requires-Dist: in-place (>=0.4.0)
Requires-Dist: nmm (>=0.0.14)
Requires-Dist: numpy (>=1.18.1)
Requires-Dist: pandas (>=1.1.2)
Requires-Dist: pytest (>=5.3.5)
Requires-Dist: tqdm (>=4.42.1)
